{
  "url": "https://www.linkedin.com/in/emmanuel-uramutse-b18a53219/",
  "scraped_at": "2025-10-27T15:25:03.630680",
  "extracted": {
    "name": "Emmanuel URAMUTSE",
    "headline": "High School Science Teacher at Science Teacher",
    "full_text": "0 notifications total\nSkip to search\nSkip to main content\nKeyboard shortcuts\nClose jump menu\nnew feed updates notifications\nHome\nMy Network\nJobs\nMessaging\nNotifications\nMe\nFor Business\nAdvertise\nEmmanuel URAMUTSE\n  \n2nd degree connection\n2nd\nHigh School Science Teacher at Science Teacher\nKigali, Kigali City, Rwanda  Contact info"
  }
}