{
  "url": "https://www.linkedin.com/in/maxime-weidema-82863239/",
  "scraped_at": "2025-10-30T11:43:50.967588",
  "extracted": {
    "name": "Maxime Weidema",
    "headline": "From Ego to Eco | From gray to \ud83c\udff3\ufe0f\u200d\ud83c\udf08",
    "full_text": "Maxime Weidema\n\nShe/Her\n\n\u00b7 2nd\n\nFrom Ego to Eco | From gray to \ud83c\udff3\ufe0f\u200d\ud83c\udf08\n\nNetherlands\n\n\u00b7\n\nContact info\n\nFreelance\n\n500+\n\nconnections\n\nWessel, Shinta and 1 other mutual connection\n\nConnect\nMessage\nActivity\n\n779 followers\n\nFollow\nPosts\nComments\n\nMaxime Weidema \u2022 2nd\n\nFrom Ego to Eco | \nFrom gray to \ud83c\udff3\ufe0f\u200d\ud83c\udf08\n\n11mo \u2022 \n\nTwee weken geleden kreeg ik Rosan Kocken op bezoek, gedeputeerde Noord-Holland met oa portefeuille op natuur en klimaat. We maakten een tour langs positieve projecten waar mensen het heft in eigen hand nemen voor vergroening van buurten; meer groen, biodiversiteit, gezondheid, plezier, schoonheid, gezamenlijkheid... noem maar op. \n\nEr zit best veel energie en motivatie bij allerlei individuen en groepen, maar er is wel ondersteuning nodig vanuit beleidsmakers: faciliteren, makkelijk maken. Dus daar spraken wij over. Je loopt snel vast in regels en bureaucratie als je iets voor mekaar wil krijgen, en dat is demotiverend. Om vanuit mijn werk voor #MeerBomenNu boompjes aan te bieden aan dit soort projecten, gratis en met extra handjes vanuit allerlei kanten, daar zit een soort katalysator, ieders energie wordt vergroot door samen iets concreets voor mekaar te krijgen. Mensen zijn enthousiast over de hoeveelheid boompjes die ze mee krijgen, de hele buurt wordt vervolgens opgetrommeld, de plaatselijk groenbeheerder helpt met een ecologisch plan, de bakker om de hoek regelt koek en taart voor in de pauze.. etc. Zo wordt energie vergroot en ingezet in een praktisch concreet project, waar de hele buurt en de natuur (insecten, e.d.) profijt bij hebben. \nDank voor je bezoek Rosan Kocken, voor je interesse om samen te zoeken naar mogelijkheden hoe we elkaar kunnen helpen, jij kan het een, wij het ander, en hoe dat samen te brengen. Wordt vervolgd! \nEn ondertussen gaan wij door met oogsten en planten van zaailingen, door heel Nederland. Ben je nieuwsgierig? Ga ook een dag mee (met mij) en leer van alles over deze vergroeningsmethode. Stuur mij een bericht of ga naar www.meerbomen.nu\n\u2026 more\n\nShow translation\n\nGroen Kapitaal\n\n2,090 followers\n\n11mo \u2022 \n\nZaterdag waren we met het team Groen Kapitaal samen met gedeputeerde Rosan Kocken op pad met Meer Bomen Nu. \n\nRosan Kocken: \u201cWe zijn als Provincie Noord-Holland partner van MeerBomenNu. Zij verzamelen de overdaad aan jonge struiken en bomen in natuur- en groengebieden, die anders bijvoorbeeld weggemaaid zullen worden. Vervolgens delen zij deze weer uit aan boeren en voedselbossen, of inwoners die sneller hun eigen omgeving willen vergroenen. Hoe tof is dat?! \n\nIk was bij de bomenhub in Hoofddorp: daar komen bomen en struiken van verschillende oogstdagen van verschillende locaties bij elkaar en worden ze tijdelijk opgeslagen, tot ze worden opgehaald om ergens geplant te worden.\n\nMeerBomenNu wordt steeds professioneler en er zijn steeds meer partijen die graag samen willen werken,\u00a0bewonersinitiatieven,\u00a0terreinbeheerders, bedrijven en ook steeds meer gemeenten in Noord-Holland (en ook in andere provincies!).\n\nAlles is gereed voor een nieuw plantseizoen. \nIn Noord-Holland worden op deze manier jaarlijks 150.000 bomen en struiken geplant! Ik hoop dat nog veel meer mensen en organisaties aansluiten in deze positieve beweging naar meer bomen, zie alle mogelijkheden op hun website www.meerbomen.nu\u201d\n\u2026 more\n\nShow translation\n\n1/4\n\n18 reactions\n18\n\n1 comment\n\nLike\nComment\nRepost\nSend\n\nMaxime Weidema \u2022 2nd\n\nFrom Ego to Eco | \nFrom gray to \ud83c\udff3\ufe0f\u200d\ud83c\udf08\n\n1yr \u2022 Edited \u2022 \n\n\ud83c\udf31De aanmelding is open voor Het Groene Traineeship vanaf deze herfst. Voor iedereen tussen 16 en 29 jaar: ga mee de natuur in en vergroen je omgeving, kom op voor de rechten van de natuur en inspireer en betrek anderen! \n\nMet MeerBomenNu zijn we onderdeel van het groen traineeship en begeleid ik een groep in de regio Amsterdam/Heemstede/Haarlemmermeer. We gaan ons inzetten voor meer bomen en biodiversiteit, terwijl we met elkaar onderzoeken hoe we de inclusiviteit en diversiteit van dit soort activiteiten en educatie kunnen vergroten. \n\nIk heb heel veel zin in om met een jonge groep te filosoferen, plannen uit te werken, mooie natuurwerkdagen te organiseren, te reflecteren en veel van elkaar te leren. Dus, ben of ken je iemand die dit leuk vindt? \nKijk voor meer informatie en aanmelden op: https://ap.lc/UxCYR\n\nOf heb je idee\u00ebn om bij te dragen aan dit programma? Bijv. door het geven van een training, stuur mij een bericht!\n\n#groentraineeship #meerbomennu #jongeren #biodiversiteit #vergroenen\n\nShow translation\n\n25 reactions\n25\n\n2 comments\n\n\u2022\n\n1 repost\n\nLike\nComment\nRepost\nSend\n\nMaxime Weidema \u2022 2nd\n\nFrom Ego to Eco | \nFrom gray to \ud83c\udff3\ufe0f\u200d\ud83c\udf08\n\n1yr \u2022 \n\nAanstaande zondag is het zo ver: de Climate Chain. We slaan letterlijk onze handen ineen langs de Nederlandse kust en maken zo een menselijke ketting met als signaal: meer en snellere actie om klimaatverandering tegen te gaan. Kom je mee? \u2764\ufe0f Ik ga naar Zandvoort en iedereen is zeer welkom aan te sluiten\n\n#theclimatechain #klimaatactie #samen #duikjenemen \n\nShow translation\n\nUrgenda\n\n25,689 followers\n\n1yr \u2022 \n\n\u2757\ufe0f\u2757\ufe0f Over een kleine twee weken is het zo ver \u2757\ufe0f\u2757\ufe0f \n\nOp zondag 23 juni slaan we om 14:00 uur, 10 minuten de handen ineen en vormen zo een menselijke ketting. Deze Climate Chain maken we om de stille meerderheid die zich zorgen maakt over klimaatverandering zichtbaar te maken.\n\nTrommel dus nog al je vrienden, ouders, (vage \u00e9n verre) kennissen, collega's, buren, leraren, ouders en alle anderen op om ook naar het strand te komen en meld je aan! Samen geven we een krachtig signaal af: we willen meer \u00e9n snellere actie om klimaatverandering tegen te gaan.\n\nMeld je aan via de website https://lnkd.in/ePJ9i4y9\n\n#jointhechain #ikbenerbij #theclimatechain \n\u2026 more\n\nShow translation\n\n3 reactions\n3\n\n1 comment\n\nLike\nComment\nRepost\nSend\n\nMaxime Weidema \u2022 2nd\n\nFrom Ego to Eco | \nFrom gray to \ud83c\udff3\ufe0f\u200d\ud83c\udf08\n\n1yr \u2022 \n\nIk doe mee aan The Climate Chain! Ga je mee? \u2764\ufe0f \n\nUrgenda\n\n25,689 followers\n\n1yr \u2022 \n\n\ud835\uddea\ud835\uddd8 \ud835\udded\ud835\udddc\ud835\udddd\ud835\udde1 \ud835\udddf\ud835\udde2\ud835\udde6: \ud835\udddd\ud835\udde2\ud835\udddc\ud835\udde1 \ud835\udde7\ud835\udddb\ud835\uddd8 \ud835\uddd6\ud835\udddf\ud835\udddc\ud835\udde0\ud835\uddd4\ud835\udde7\ud835\uddd8 \ud835\uddd6\ud835\udddb\ud835\uddd4\ud835\udddc\ud835\udde1!\n\nOp zondag 23 juni 2024 slaan we de handen ineen en trekken een rode streep langs de Nederlandse kustlijn. Samen vormen we een human chain en vragen we snellere actie tegen ontwrichtende klimaatverandering en voor een volhoudbare economie. Zo maken we het grote draagvlak voor meer en snellere klimaatactie zichtbaar. Een meerderheid van de Nederlanders sprak zich in 2023 uit voor meer klimaatbeleid en vraagt meer actie van de overheid.\n\n\ud83c\udf0e \ud835\uddea\ud835\uddee\ud835\ude01 \ud835\uddf4\ud835\uddee\ud835\uddee\ud835\uddfb \ud835\ude04\ud835\uddf2 \ud835\uddf1\ud835\uddfc\ud835\uddf2\ud835\uddfb? We vormen de langste human chain ooit langs de Nederlandse kust: de grootste letterlijke verbinding van mensen in Nederland voor meer klimaatactie.\n\ud83d\udc65 \ud835\udde9\ud835\uddfc\ud835\uddfc\ud835\uddff \ud835\ude04\ud835\uddf6\ud835\uddf2? Voor iedereen die meer en snellere actie wil om ontwrichtende klimaatverandering te voorkomen.\n\ud83d\uddd3\ufe0f \ud835\uddea\ud835\uddee\ud835\uddee\ud835\uddff \ud835\uddf2\ud835\uddfb \ud835\ude04\ud835\uddee\ud835\uddfb\ud835\uddfb\ud835\uddf2\ud835\uddf2\ud835\uddff? Op zondag 23 juni om 14:00 uur, op een kustlocatie bij jou in de buurt.\n\nWe hebben de Nederlandse kust opgedeeld in vakken van elk \u00e9\u00e9n kilometer. Via de kaart op de website kun je je aanmelden voor het vak waar jij, je familie, vrienden en collega's willen staan. Claim snel jouw favoriete kustlocatie via de website https://theclimatechain.nl\n\nTot zondag 23 juni bij The Climate Chain!\n\n#TheClimateChain #VerbindenVoorVersnelling\n\u2026 more\n\nShow translation\n\n7 reactions\n7\n\n2 comments\n\n\u2022\n\n1 repost\n\nLike\nComment\nRepost\nSend\n\nMaxime Weidema \u2022 2nd\n\nFrom Ego to Eco | \nFrom gray to \ud83c\udff3\ufe0f\u200d\ud83c\udf08\n\n2yr \u2022 \n\nWe gaan bijna weer beginnen \ud83c\udf33 \ud83c\udf33 \nPer week een keertje minder naar de sportschool en met mij mee het bos in!! Gegarandeerd genoeg beweging, frisse lucht, geestelijke ontspanning, gezelligheid, uitdaging, nieuwe kennis over ecologie en bomen, en natuurlijk de voldoening door bij te dragen aan biodiversiteit en klimaatproblematiek. \nJa, ook JIJ kan mee doen. Tot binnenkort dus. \n\nShow translation\n\nMeer Bomen Nu\n\n5,064 followers\n\n2yr \u2022 \n\n\ud83c\udf33 NU: GRATIS BOMEN \ud83c\udf33\n\nIn het Algemeen Dagblad:  Het vierde seizoen van Meer Bomen Nu gaat van start en iedereen kan nu gratis (inheemse) bomen en struiken aanvragen op meerbomen.nu of de (gloednieuwe) app downloaden in apple en playstore!\n\nOok kan iedereen die de handen uit de mouwen wil steken voor #klimaat en #biodiversiteit aanhaken om te helpen kansarme zaailingen een tweede kans te geven.\n\n\"Iedereen met een gezonde dosis enthousias\u00adme en een schep kan meedoen. Groene vingers zijn niet vereist\"\n\nLees het hele artikel: \ud83d\udc49 https://lnkd.in/ehm3ANFB\n\nEen initiatief van Urgenda, Caring Farmers en Stichting MEERGroen\n\nMarjan Minnesma Marga Witteman Tsjeard Hofstra Mehr B\u00e4ume Jetzt Aukje Romkes Stefan Forsten Floor Verdenius Elsemarieke Spriensma Bonnie Snoek Frank de Waal Stijn Mertens Anouk Guilliet Leonie Caesar Marc Rotmans Ids Toxopeus L\u00e9on Uittenbogaard Hanneke van Ormondt\n\u2026 more\n\nShow translation\n\nNederland krijgt er komende maanden 600.000 bomen bij\n\nad.nl\n\n8 reactions\n8\n\n3 comments\n\nLike\nComment\nRepost\nSend\n\nMaxime Weidema \u2022 2nd\n\nFrom Ego to Eco | \nFrom gray to \ud83c\udff3\ufe0f\u200d\ud83c\udf08\n\n2yr \u2022 Edited \u2022 \n\nNature's beauty\nWith Stichting MEERGroen we created 50 flower meadows on more than 20 acres, in cooperation with municipalities and companies. From now until September these bloom with different species each time. All with the aim of more biodiversity, food for bees and other pollinators, and to offer us fascinating views! \u2764\ufe0f Look around and enjoy nature's beauty!\n#biodiversity #flowermeadow #beauty #bees \n\n17 reactions\n17\n\n2 reposts\n\nLike\nComment\nRepost\nSend\n\nMaxime Weidema \u2022 2nd\n\nFrom Ego to Eco | \nFrom gray to \ud83c\udff3\ufe0f\u200d\ud83c\udf08\n\n2yr \u2022 \n\nStichting MEERGroen\n\n536 followers\n\n2yr \u2022 \n\n\ud83c\udf33\ud83c\udf0d\ud83c\uddee\ud83c\uddf9 MEERGroen maakt grote stappen in Itali\u00eb: samenwerkingen, bomen planten en een duurzame toekomst! \ud83c\udf33\ud83c\udf0d\ud83c\uddee\ud83c\uddf9\n\nWe zijn net terug van een inspirerende 2-weekse reis naar Itali\u00eb, waar we onze ecologische inspanningen hebben uitgebreid naar nieuwe horizonten. Ons doel is om wereldwijd het ecologische wanbeheer aan te pakken, en Itali\u00eb was de perfecte plek om ons bereik te vergroten.\n\nWe hebben ons gericht op twee hoofddoelen: het vinden van lokale partners en het uitvoeren van overlevingsstudies in het mediterrane klimaat. We hebben contact gelegd met de \"17 tons\" beweging in Itali\u00eb, die aansluit bij onze missie om jaarlijks 17 ton CO2 per persoon te verwijderen. Samen maken we een grote impact!\n\nWe hebben productieve vergaderingen gehad met Lega Ambiente Umbria en verschillende boomkwekerijen, waarbij we mogelijkheden hebben verkend om meer bomen te planten en duurzame praktijken te bevorderen. De Paulownia boom trok onze aandacht, omdat deze gedijt in het Italiaanse klimaat en een CO2-afvang kampioen is. Door Paulownia bomen te planten, kunnen we een groenere en gezondere toekomst cre\u00ebren.\n\nTijdens onze reis hebben we onze ervaringen gedocumenteerd en video's en materialen in het Italiaans gemaakt ter ondersteuning van de Pi\u00f9AlberiOra campagne. De positieve energie en enthousiasme die we zijn tegengekomen, waren echt inspirerend!\n\nBij terugkomst waren we verheugd te zien dat onze toegewijde vrijwilligers goed voor de tuinen hadden gezorgd in onze afwezigheid. Samen blijven we wieden, groenten oogsten en onze gezamenlijke verantwoordelijkheid voor een groenere wereld koesteren.\n\nMaar onze inspanningen stopten niet in Itali\u00eb! Een van onze teamleden heeft deelgenomen aan de ChangeNOW-conferentie in Parijs en onderzocht samenwerkingen met Franse boomplantinitiatieven. We overwegen zelfs samenwerking met de duurzaamheidsambities van de Olympische Spelen van 2026!\n\nDoe met ons mee om een verschil te maken en een duurzame toekomst voor iedereen op te bouwen. Samen kunnen we geweldige dingen bereiken! \ud83c\udf33\ud83d\udc9a\n\n#MoreGreenMission #DuurzaamLeven #BoomPlanten #MilieuImpact #GlobaleSamenwerking #ChangeNOW #2026Olympics #MEERGroen #MeerBomenNu #PiuAlberiOra\n\n\u2026 more\n\nShow translation\nLike\nComment\nRepost\nSend\n\nMaxime Weidema \u2022 2nd\n\nFrom Ego to Eco | \nFrom gray to \ud83c\udff3\ufe0f\u200d\ud83c\udf08\n\n2yr \u2022 Edited \u2022 \n\nBen je een voedselbos aan het cre\u00ebren? \ud83c\udf33 Wil je meer biodiversiteit in je tuin? \ud83d\udc1d Heb je een stuk(je) grond en wil je meer bomen of struiken planten? \ud83c\udf39   \nWe hebben deze winter met MeerBomenNu door heel Nederland veel kleine boompjes geoogst, die elders in overdaad waren of het anders niet zouden redden. Deze zijn nu op zoek naar een nieuw thuis. We\u00a0geven je gratis een leuke en voor jou geschikte mix aan\u00a0bomen en struiken mee: voor een mooie leefomgeving, om de biodiversiteit \u00e9n het klimaat te helpen. Er zijn allerlei verschillende soorten, denk aan de hazelaar, esdoorn, berk, wilg, zwarte els, es, beuk, eik, kastanje en kers, en bijvoorbeeld ook de vlieren- en vlinderstruik. \nWees welkom op de uitdeeldagen van Stichting MEERGroen in de Haarlemmermeer: 12, 15 of 18 maart in Aalsmeer, Hoofddorp of Sassenheim. Aanmelden: https://bit.ly/41vMY1m\nWoon je elders in het land? Op 4 maart zijn er door het hele land uitdeeldagen. Bekijk alle plekken en meld je aan: https://lnkd.in/e9Vi776Q\n\n#GratisBomen #Klimaat #Biodiversiteit #MEERGroen #Bomenactie\n\u2026 more\n\nShow translation\n\n12, 15 en 18 maart: Gratis bomen voor iedereen: op inschrijving\n\nbit.ly\n\n18 reactions\n18\n\n1 comment\n\n\u2022\n\n1 repost\n\nLike\nComment\nRepost\nSend\n\nMaxime Weidema \u2022 2nd\n\nFrom Ego to Eco | \nFrom gray to \ud83c\udff3\ufe0f\u200d\ud83c\udf08\n\n2yr \u2022 \n\n\ud83c\udf31\ud83c\udf33 Oooh wat is de natuur krachtig, prachtig, helend, en zo belangrijk in de uitdagingen van deze maatschappij.. Ik leefde 1,5 jaar te midden van pure natuur, eerst in een ecologische gemeenschap, en daarna in een klein dorpje in de bergen. Nu ben ik weer thuis, in Nederland, in Amsterdam. Daar was mijn relatie tot de natuur anders, je voelt je nederiger, meer verbonden. Hier voelt het meer afgescheiden, je hebt de stad, en je hebt het bos/heide/etc.\u00a0\nDe vraag \u2018hoe verhouden wij ons tot de natuur\u2019 is een grote en cruciale in de transitie naar een duurzame toekomst. Het besef groeit dat we onderdeel zijn van de natuur, \u00e9n dat we er goed voor moeten zorgen. Maar hoe geven we daar vorm aan? In mijn zoektocht vind ik een antwoord in dit initiatief, niet in woorden, maar in actie: \n\n\ud83c\udf31\ud83c\udf33 Stichting MEERGroen, met oa de campagne MeerBomenNu (ism Urgenda en Caring Farmers).\n\nHet is een bottom-up initiatief, waar burgers zich op verschillende plekken vrijwillig inzetten voor lokaal ecologisch beheer, via allerlei georganiseerde activiteiten. Ipv je machteloos voelen, of wachten op politiek en bedrijfsleven, verantwoordelijkheid nemen en aan de slag gaan. We (ver)planten bomen, leggen bloemenweides aan, vergroten biodiversiteit, toveren braakliggende grond om in ecologische paradijsjes, en meer. Het is een verhaal van hoop, verbeelding, empowerment, actie. Een beweging richting een andere relatie met de natuur. Wij zijn er onderdeel van, we voeden het ecosysteem, we ondersteunen de natuur om ons heen. En niet te vergeten, de natuur voedt altijd terug! Je voelt je ontspannen, energiek, gezond en verbonden met natuur en medemens. \n\nIk verbeeld me alvast een wereld waar dit normaal is, en nodig daarom iedereen uit om een keertje mee te gaan, dit kan door heel Nederland, zie hier de planning https://lnkd.in/eYYYcUmg\n\n#meergroen #meernatuur #meerbomen #biodiversiteit #actie #vrijwilligers #doemee\n\u2026 more\n\nShow translation\n\nAgenda - MeerBomenNu\n\nmeerbomen.nu\n\n32 reactions\n32\n\n6 comments\n\n\u2022\n\n1 repost\n\nLike\nComment\nRepost\nSend\n\nMaxime Weidema \u2022 2nd\n\nFrom Ego to Eco | \nFrom gray to \ud83c\udff3\ufe0f\u200d\ud83c\udf08\n\n5yr \u2022 Edited \u2022 \n\nWhere the first few 'Corona months' have literally and spiritually been a journey inside, the last weeks, it was time to open up more, connect and give: I participated in the Bright Minds program of Impact Hub Amsterdam & Young Impactmakers Community & Starters4Communities. Big shout out to my team Abi Malins Lenka Homolka Liza Anceaux, what a smooth collaboration, lovely women. \n\nGreat thanks to Rutger de Rijk and his team for connecting me to the exemplary and inspiring Bloei & Groei initiative that empowers women in Amsterdam Zuid-Oost through gardening, and for which we explored partnership options. It pointed out even more how vital it is to spend time outside, connecting with people and nature. \n\nTo continue and integrate this more into my own life as well, I am currently spending my days at my favorite campsite in the north of the Netherlands, Camping BuitenLand, where I have offered to work on improving its sustainability (i.e. waste streams, veg&herb garden, increase awareness among guests and employees). My experience working with Green Events Nederland, greening the festival industry, will come in handy. If anyone has experience with greening campsites in particular, would love to exchange thoughts.\n\n#brightminds #youngimpactmakers #sustainability #campsite\n\u2026 more\n\n1/2\n\n61 reactions\n61\n\n6 comments\n\n\u2022\n\n1 repost\n\nLike\nComment\nRepost\nSend\nShow all\nExperience\n\nProject, process & community coordinator \n\nFreelance \u00b7 Freelance\n\nJan 2025 - Present \u00b7 10 mos\n\nAmsterdam, North Holland, Netherlands \u00b7 Hybrid\n\nReach out to set-up, create and run beautiful green&people projects together. maxime@denatuurbende.nl\n\nProject- en procesbegeleider met focus op bewustwording en eigenaarschap rond natuur\n\nEcoco \u00b7 Part-time\n\nDec 2024 - Present \u00b7 11 mos\n\nNetherlands \u00b7 Hybrid\n\nCoordinator Noord-Holland & Coordinator company days \n\nMeerBomenNu\n\nJun 2023 - Present \u00b7 2 yrs 5 mos\n\nNetherlands\n\nCampaign for circular tree planting to fight climate change and create more biodiversity\n\nProject & community coordinator\n\nStichting MEERGroen\n\nOct 2022 - May 2025 \u00b7 2 yrs 8 mos\n\nNetherlands\n\nBottom-up ecological management, nature development and urban farming\n\nCoordinator of Work and Volunteers \n\nECOLONIE CENTRE ECOLOGIQUE INTERNATIONAL\n\nJun 2021 - Mar 2022 \u00b7 10 mos\n\nFrance\n\nECOlonie\n\n Interpersonal Communication, Problem Solving and +5 skills\n\nShow all\nEducation\n\nPhoenix Opleidingen\n\npost-HBO Registeropleiding, Opleiding in Professionele Communicatie\n\nSep 2024 \u2013 Aug 2027\n\nScholing tot begeleider van ontwikkelingsprocessen op persoonlijk en organisatieniveau. \nPijlers: autonomie, heelheid, identiteit, integratie en zingeving\nStromingen: TA, NLP en Systemisch Werken\n\u2026 more\n\nOpleiding in professionele communicatie (3 oktober 2024)\n\nVrije Universiteit van Amsterdam & Universiteit van Amsterdam (Joint programme)\n\nMaster of Science (MSc), Research Master - Business in Society\n\n2015 \u2013 2017\n\nAbout the MSc program Business in Society: it addresses the intricate relationships between business and society, as can be seen in grand challenges posed by e.g. the financial crisis, society\u2019s request for ethical leadership and corporate social responsibility, and the need for sustainability. This program educates a new generation of business researchers who will have a profound grasp of the societal trends that are changing the face of business.\n\nAbout my research focus: I examined the role of crowdsourcing - functioning as an open, multi-stakeholder, problem-centered form of organizing - in tackling the grand societal challenge of climate crisis. \n\n\n\u2026 more\n\nShow all\nSkills\n\nArt of creation \n\nCoordinator of Work and Volunteers  at ECOLONIE CENTRE ECOLOGIQUE INTERNATIONAL\n\nInterpersonal Communication\n\nCoordinator of Work and Volunteers  at ECOLONIE CENTRE ECOLOGIQUE INTERNATIONAL\n\n1 endorsement\n\nShow all\nLanguages\n\nDutch\n\nNative or bilingual proficiency\n\nEnglish\n\nFull professional proficiency\n\nShow all\nInterests\nTop Voices\nCompanies\nGroups\nNewsletters\nSchools\n\nHarald Friedl \n\n\u00b7 2nd\n\nCircular Economy & Sustainability Strategist | Public Speaker | Leadership Coach | Impact Storytelling | Transforming Systems from Ego to Eco\n\n124,930 followers\n\nMessage\nCauses\n\nAnimal Welfare \u2022 Arts and Culture \u2022 Civil Rights and Social Action \u2022 Disaster and Humanitarian Relief \u2022 Environment \u2022 Human Rights \u2022 Politics \u2022 Poverty Alleviation\n\nPeople also viewed\n\nFranke van der Laan\n\n\u00b7 2nd\n\nClimate Mayor Haarlemmermeer 2021-2025| Initiator @meerbomen.nu | Director @StichtingMEERGroen; Citizin of honor Municipality Ouder Amstel at age of 25 ; 3x in National Sustainable Top100 on spot 18, 56,\n\nConnect\n\nJoost Gringhuis\n\n\u00b7 3rd\n\nWOZ- co\u00f6rdinator  bij Gemeente Den Haag\n\nMessage\n\nLeon ter Linden \n\n\u00b7 3rd\n\nWerkt graag samen naar een duurzamere samenleving | Bestuurslid De Groene Transformator | Software engineer Groene Code\n\nMessage\n\nIris van der Haagen\n\n\u00b7 3rd\n\nBaking bread\n\nMessage\n\nPascalle Van der Ven\n\n\u00b7 3rd\n\nCo\u00f6rdinator Dierenambulance\u2019s-Hertogenbosch e.o.\n\nConnect\nShow all\n\nExplore premium profiles\n\nSusan Kelly \n\n\u00b7 3rd\n\nDriving Innovation in Document Search & Access | President @ MicroSearch | JD, Boston College\n\nMessage\n\nXavier Delacour \n\n\u00b7 3rd\n\nFounder at Occam Vision Group\n\nMessage\n\nYooRi Kim \n\n\u00b7 3rd\n\nNonprofit Entrepreneur & Philanthropy Advisor\n\nMessage\n\nDuke Pham \n\n\u00b7 3rd\n\nFounder at Phonomenal, Inc\n\nMessage\n\nPeople you may know\n\nFrom Maxime's school\n\nJoszi Smeets\n\n\u00b7 2nd\n\nCo Founder, Creative Director Food Hub\n\nConnect\n\nLinde Lassche \n\n\u00b7 2nd\n\nVenture Capital | Impact Investing | Board Member\n\nConnect\n\nCorriene van Eck\n\n\u00b7 3rd\n\nProgrammamanager bij KnopOm | Einde maken aan energiearmoede | Meetbare maatschappelijke impact & ondernemerschap\n\nMessage\n\nJanneke Leenaars\n\n\u00b7 2nd\n\nSustainability Manager Northern Europe at Interface\n\nConnect\n\nDaniel Reisman\n\n\u00b7 2nd\n\nCo-Founder | Chief of Growth & Relations at Collie\n\nConnect\nShow all\n\nYou might like\n\nNewsletters for you\n\nTHRIVE\n\nTransform your relationship with practical advice and expert guidance from Coaches Taf and Victoria.\n\nPublished monthly\n\nTafazal Mohammed - Muslim Men\u2019s Coach, MA, PG Dip\n\nSubscribe\n\nGenerations\n\nGenerative Media Creative Tips, Tricks, Tools & Secret Recipes\n\nPublished monthly\n\nEvo H.\n\nSubscribe\nShow all\n\nAbout\n\nAccessibility\n\nTalent Solutions\n\nCommunity Guidelines\n\nCareers\n\nMarketing Solutions \n\nPrivacy & Terms\n\nAd Choices\n\nAdvertising\n\nSales Solutions\n\nMobile\n\nSmall Business\n\nSafety Center\n\nLinkedIn Corporation \u00a9 2025\n\nQuestions?\n\nVisit our Help Center.\n\nManage your account and privacy\n\nGo to your Settings.\n\nRecommendation transparency\n\nLearn more about Recommended Content.\n\nSelect language\n\n\u0627\u0644\u0639\u0631\u0628\u064a\u0629 (Arabic)\n\u09ac\u09be\u0982\u09b2\u09be (Bangla)\n\u010ce\u0161tina (Czech)\nDansk (Danish)\nDeutsch (German)\n\u0395\u03bb\u03bb\u03b7\u03bd\u03b9\u03ba\u03ac (Greek)\nEnglish (English)\nEspa\u00f1ol (Spanish)\n\u0641\u0627\u0631\u0633\u06cc (Persian)\nSuomi (Finnish)\nFran\u00e7ais (French)\n\u0939\u093f\u0902\u0926\u0940 (Hindi)\nMagyar (Hungarian)\nBahasa Indonesia (Indonesian)\nItaliano (Italian)\n\u05e2\u05d1\u05e8\u05d9\u05ea (Hebrew)\n\u65e5\u672c\u8a9e (Japanese)\n\ud55c\uad6d\uc5b4 (Korean)\n\u092e\u0930\u093e\u0920\u0940 (Marathi)\nBahasa Malaysia (Malay)\nNederlands (Dutch)\nNorsk (Norwegian)\n\u0a2a\u0a70\u0a1c\u0a3e\u0a2c\u0a40 (Punjabi)\nPolski (Polish)\nPortugu\u00eas (Portuguese)\nRom\u00e2n\u0103 (Romanian)\n\u0420\u0443\u0441\u0441\u043a\u0438\u0439 (Russian)\nSvenska (Swedish)\n\u0c24\u0c46\u0c32\u0c41\u0c17\u0c41 (Telugu)\n\u0e20\u0e32\u0e29\u0e32\u0e44\u0e17\u0e22 (Thai)\nTagalog (Tagalog)\nT\u00fcrk\u00e7e (Turkish)\n\u0423\u043a\u0440\u0430\u0457\u043d\u0441\u044c\u043a\u0430 (Ukrainian)\nTi\u1ebfng Vi\u1ec7t (Vietnamese)\n\u7b80\u4f53\u4e2d\u6587 (Chinese (Simplified))\n\u6b63\u9ad4\u4e2d\u6587 (Chinese (Traditional))"
  }
}